vis4wave/__init__.py
vis4wave/demo_wave_network.py
vis4wave/network.py
vis4wave/wave_events.py
pyvis4wave-0.0.2.dist-info/LICENSE
pyvis4wave-0.0.2.dist-info/METADATA
pyvis4wave-0.0.2.dist-info/WHEEL
pyvis4wave-0.0.2.dist-info/top_level.txt
pyvis4wave-0.0.2.dist-info/RECORD
