Metadata-Version: 2.1
Name: pyvis4wave
Version: 0.0.2
Summary: Bring interactive network visualization to H2O wave web-apps
Author: Jean-Matthieu Schertzer
Classifier: Intended Audience :: Developers
Classifier: Intended Audience :: Science/Research
Classifier: Programming Language :: Python :: 3
Classifier: Programming Language :: Python :: 3.6
Classifier: Programming Language :: Python :: 3.7
Classifier: Programming Language :: Python :: 3.8
Classifier: License :: OSI Approved :: Apache Software License
Classifier: Topic :: Scientific/Engineering
Classifier: Topic :: Scientific/Engineering :: Artificial Intelligence
Classifier: Topic :: Scientific/Engineering :: Visualization
License-File: LICENSE
Requires-Dist: pyvis (>=0.1.9)
Requires-Dist: h2o-wave (>=0.16.0)
Provides-Extra: dev
Requires-Dist: mkdocs (==1.1) ; extra == 'dev'
Requires-Dist: mkdocs-material (==4.6.3) ; extra == 'dev'
Requires-Dist: mkdocstrings (==0.8.0) ; extra == 'dev'
Requires-Dist: flake8 (>=3.6.0) ; extra == 'dev'
Requires-Dist: nbval (>=0.9.1) ; extra == 'dev'
Requires-Dist: pytest (>=4.0.2) ; extra == 'dev'
Requires-Dist: pytest-xdist (>=1.32.0) ; extra == 'dev'
Requires-Dist: black (>=19.3b0) ; extra == 'dev'
Requires-Dist: pytest-cov (>=2.6.1) ; extra == 'dev'
Requires-Dist: pytest-mock (>=1.6.3) ; extra == 'dev'
Requires-Dist: pre-commit (>=1.18.3) ; extra == 'dev'
Requires-Dist: nbval (>=0.9.6) ; extra == 'dev'
Requires-Dist: mktestdocs (==0.1.1) ; extra == 'dev'
Requires-Dist: jupyter (>=1.0.0) ; extra == 'dev'
Provides-Extra: docs
Requires-Dist: mkdocs (==1.1) ; extra == 'docs'
Requires-Dist: mkdocs-material (==4.6.3) ; extra == 'docs'
Requires-Dist: mkdocstrings (==0.8.0) ; extra == 'docs'
Provides-Extra: test
Requires-Dist: flake8 (>=3.6.0) ; extra == 'test'
Requires-Dist: nbval (>=0.9.1) ; extra == 'test'
Requires-Dist: pytest (>=4.0.2) ; extra == 'test'
Requires-Dist: pytest-xdist (>=1.32.0) ; extra == 'test'
Requires-Dist: black (>=19.3b0) ; extra == 'test'
Requires-Dist: pytest-cov (>=2.6.1) ; extra == 'test'
Requires-Dist: pytest-mock (>=1.6.3) ; extra == 'test'
Requires-Dist: pre-commit (>=1.18.3) ; extra == 'test'
Requires-Dist: nbval (>=0.9.6) ; extra == 'test'
Requires-Dist: mktestdocs (==0.1.1) ; extra == 'test'
